clearconf/__init__.py
clearconf/api/_utils/misc.py
clearconf/api/_utils/pickle_reduce.py
clearconf/api/base_config.py
clearconf/api/exceptions.py
clearconf/api/meta.py
clearconf/api/node.py
clearconf/api/root.py
clearconf/api/tree_functions.py
clearconf/api/types.py
clearconf/assets/example_conf.py
clearconf/assets/init.py
clearconf/assets/stub_conf.py
clearconf/cli/__init__.py
clearconf/cli/defaults.py
clearconf/cli/main.py
clearconf/utils/__init__.py
clearconf/utils/conf.py
clearconf/utils/file.py
clearconf/utils/stdout.py
clearconf-0.3.22.dist-info/LICENSE
clearconf-0.3.22.dist-info/METADATA
clearconf-0.3.22.dist-info/WHEEL
clearconf-0.3.22.dist-info/entry_points.txt
clearconf-0.3.22.dist-info/RECORD
