Metadata-Version: 2.3
Name: clearconf
Version: 0.3.22
Summary: ClearConf is a library created to support easy and manageble python configuration. It consists in a CLI tool to manage the configuration directory, and in a python class (BaseConfig) which adds additional functionalities to a configuration class.
Author: Andrea Rosasco
Author-email: andrearosasco.ar@gmail.com
Requires-Python: >=3.8,<4.0
Classifier: Programming Language :: Python :: 3
Classifier: Programming Language :: Python :: 3.8
Classifier: Programming Language :: Python :: 3.9
Classifier: Programming Language :: Python :: 3.10
Classifier: Programming Language :: Python :: 3.11
Classifier: Programming Language :: Python :: 3.12
Classifier: Programming Language :: Python :: 3.13
Requires-Dist: typer (>=0,<1)
Project-URL: Homepage, https://github.com/andrearosasco/clearconf
Project-URL: Repository, https://github.com/andrearosasco/clearconf
